__init__.py
aws_sig/__init__.py
aws_sig/_credentials.py
aws_sig/_utils.py
aws_sig/exceptions.py
aws_sig/v4.py
aws_signature-1.0.0.dist-info/LICENSE
aws_signature-1.0.0.dist-info/METADATA
aws_signature-1.0.0.dist-info/WHEEL
aws_signature-1.0.0.dist-info/top_level.txt
aws_signature-1.0.0.dist-info/RECORD
