Metadata-Version: 2.2
Name: aws-signature
Version: 1.0.0
Summary: A Python Library to Authenticate Request to the AWS API using the AWS Signatures
Author-email: Felix Cusson <felixcusson@gmail.com>
License: MIT License
Project-URL: Bug Reports, https://github.com/fcusson/aws-sig/issues
Project-URL: Source, https://github.com/fcusson/aws-sig
Keywords: aws,requests,api
Requires-Python: >=3.9
License-File: LICENSE
Requires-Dist: requests>=2.32.3
